clearview/__init__.py
clearview/consent.py
clearview-0.2.1.dist-info/METADATA
clearview-0.2.1.dist-info/WHEEL
clearview-0.2.1.dist-info/RECORD
