Metadata-Version: 2.1
Name: clearview
Version: 0.2.1
Summary: SDK for Clearview AI
Home-page: https://clearview.ai
License: MIT
Author: Clearview AI
Author-email: info@clearview.ai
Requires-Python: >=3.8,<4.0
Classifier: Environment :: Console
Classifier: License :: OSI Approved :: MIT License
Classifier: Operating System :: OS Independent
Classifier: Programming Language :: Python :: 3
Classifier: Programming Language :: Python :: 3.8
Classifier: Programming Language :: Python :: 3.9
Classifier: Programming Language :: Python :: 3.10
Classifier: Programming Language :: Python :: 3.11
Requires-Dist: filetype (>=1.0.13,<2.0.0)
Requires-Dist: requests (>=2.27.1,<3.0.0)
